kensu/__init__.py
kensu/itertools.py
kensu/pyspark/KensuDataFrameWriter.py
kensu/pyspark/__init__.py
kensu/pyspark/spark_connector.py
kensu/utils/kensu_conf_file/__init__.py
kensu/utils/kensu_conf_file/conf_file.py
kensu/utils/remote/circuit_breakers.py
kensu_pyspark-2.9.2.dist-info/LICENSE
kensu_pyspark-2.9.2.dist-info/METADATA
kensu_pyspark-2.9.2.dist-info/WHEEL
kensu_pyspark-2.9.2.dist-info/top_level.txt
kensu_pyspark-2.9.2.dist-info/RECORD
